[{"id":0,"name":"Overall","rank":976682,"level":1669,"xp":31272203},{"id":1,"name":"Attack","rank":1617118,"level":71,"xp":892395},{"id":2,"name":"Defence","rank":1441137,"level":71,"xp":895609},{"id":3,"name":"Strength","rank":1819320,"level":74,"xp":1158330},{"id":4,"name":"Hitpoints","rank":1745069,"level":76,"xp":1431949},{"id":5,"name":"Ranged","rank":1748390,"level":75,"xp":1231270},{"id":6,"name":"Prayer","rank":1108512,"level":70,"xp":770709},{"id":7,"name":"Magic","rank":1813942,"level":73,"xp":1028242},{"id":8,"name":"Cooking","rank":1119582,"level":74,"xp":1117367},{"id":9,"name":"Woodcutting","rank":820555,"level":77,"xp":1595601},{"id":10,"name":"Fletching","rank":804530,"level":78,"xp":1741065},{"id":11,"name":"Fishing","rank":1330708,"level":68,"xp":654170},{"id":12,"name":"Firemaking","rank":1345687,"level":71,"xp":855554},{"id":13,"name":"Crafting","rank":755214,"level":76,"xp":1359882},{"id":14,"name":"Smithing","rank":1133004,"level":70,"xp":752866},{"id":15,"name":"Mining","rank":1217914,"level":70,"xp":780916},{"id":16,"name":"Herblore","rank":884520,"level":70,"xp":773027},{"id":17,"name":"Agility","rank":1339224,"level":67,"xp":566244},{"id":18,"name":"Thieving","rank":1168390,"level":61,"xp":321742},{"id":19,"name":"Slayer","rank":1320573,"level":66,"xp":500353},{"id":20,"name":"Farming","rank":356136,"level":94,"xp":8502098},{"id":21,"name":"Runecraft","rank":913569,"level":60,"xp":278632},{"id":22,"name":"Hunter","rank":701308,"level":73,"xp":1070912},{"id":23,"name":"Construction","rank":352640,"level":84,"xp":2993270}]