[{"id":0,"name":"Overall","rank":976826,"level":1669,"xp":31540161},{"id":1,"name":"Attack","rank":1617264,"level":71,"xp":892612},{"id":2,"name":"Defence","rank":1441260,"level":71,"xp":895826},{"id":3,"name":"Strength","rank":1819351,"level":74,"xp":1159095},{"id":4,"name":"Hitpoints","rank":1745116,"level":76,"xp":1432352},{"id":5,"name":"Ranged","rank":1748590,"level":75,"xp":1231282},{"id":6,"name":"Prayer","rank":1108705,"level":70,"xp":770709},{"id":7,"name":"Magic","rank":1814090,"level":73,"xp":1028437},{"id":8,"name":"Cooking","rank":1119713,"level":74,"xp":1117367},{"id":9,"name":"Woodcutting","rank":820748,"level":77,"xp":1595601},{"id":10,"name":"Fletching","rank":804626,"level":78,"xp":1741065},{"id":11,"name":"Fishing","rank":1330842,"level":68,"xp":654170},{"id":12,"name":"Firemaking","rank":1345905,"level":71,"xp":855554},{"id":13,"name":"Crafting","rank":755255,"level":76,"xp":1360062},{"id":14,"name":"Smithing","rank":1133185,"level":70,"xp":752866},{"id":15,"name":"Mining","rank":1218127,"level":70,"xp":780916},{"id":16,"name":"Herblore","rank":884691,"level":70,"xp":773027},{"id":17,"name":"Agility","rank":1339445,"level":67,"xp":566244},{"id":18,"name":"Thieving","rank":1168610,"level":61,"xp":321742},{"id":19,"name":"Slayer","rank":1320749,"level":66,"xp":500353},{"id":20,"name":"Farming","rank":351961,"level":94,"xp":8763987},{"id":21,"name":"Runecraft","rank":913756,"level":60,"xp":278632},{"id":22,"name":"Hunter","rank":699956,"level":73,"xp":1074992},{"id":23,"name":"Construction","rank":352716,"level":84,"xp":2993270}]