[{"id":0,"name":"Overall","rank":998504,"level":1656,"xp":28644608},{"id":1,"name":"Attack","rank":1616023,"level":71,"xp":891513},{"id":2,"name":"Defence","rank":1440076,"level":71,"xp":894727},{"id":3,"name":"Strength","rank":1818405,"level":74,"xp":1156252},{"id":4,"name":"Hitpoints","rank":1744012,"level":76,"xp":1430659},{"id":5,"name":"Ranged","rank":1746334,"level":75,"xp":1231234},{"id":6,"name":"Prayer","rank":1107783,"level":70,"xp":770524},{"id":7,"name":"Magic","rank":1814966,"level":73,"xp":1022197},{"id":8,"name":"Cooking","rank":1206149,"level":72,"xp":940964},{"id":9,"name":"Woodcutting","rank":819205,"level":77,"xp":1595601},{"id":10,"name":"Fletching","rank":803849,"level":78,"xp":1740985},{"id":11,"name":"Fishing","rank":1329642,"level":68,"xp":654170},{"id":12,"name":"Firemaking","rank":1344239,"level":71,"xp":855554},{"id":13,"name":"Crafting","rank":765662,"level":76,"xp":1340867},{"id":14,"name":"Smithing","rank":1131441,"level":70,"xp":752866},{"id":15,"name":"Mining","rank":1233233,"level":70,"xp":769851},{"id":16,"name":"Herblore","rank":889167,"level":70,"xp":767761},{"id":17,"name":"Agility","rank":1337857,"level":67,"xp":565574},{"id":18,"name":"Thieving","rank":1166890,"level":61,"xp":321699},{"id":19,"name":"Slayer","rank":1319577,"level":66,"xp":500353},{"id":20,"name":"Farming","rank":420803,"level":91,"xp":6267879},{"id":21,"name":"Runecraft","rank":1166386,"level":52,"xp":133676},{"id":22,"name":"Hunter","rank":709767,"level":73,"xp":1046432},{"id":23,"name":"Construction","rank":351931,"level":84,"xp":2993270}]