[{"id":0,"name":"Overall","rank":972426,"level":1672,"xp":33243385},{"id":1,"name":"Attack","rank":1618352,"level":71,"xp":893414},{"id":2,"name":"Defence","rank":1441935,"level":71,"xp":896628},{"id":3,"name":"Strength","rank":1820306,"level":74,"xp":1160556},{"id":4,"name":"Hitpoints","rank":1746205,"level":76,"xp":1433383},{"id":5,"name":"Ranged","rank":1749544,"level":75,"xp":1231552},{"id":6,"name":"Prayer","rank":1109461,"level":70,"xp":770796},{"id":7,"name":"Magic","rank":1815396,"level":73,"xp":1028480},{"id":8,"name":"Cooking","rank":1120564,"level":74,"xp":1117367},{"id":9,"name":"Woodcutting","rank":821024,"level":77,"xp":1595601},{"id":10,"name":"Fletching","rank":805194,"level":78,"xp":1741065},{"id":11,"name":"Fishing","rank":1331734,"level":68,"xp":654170},{"id":12,"name":"Firemaking","rank":1346994,"level":71,"xp":855554},{"id":13,"name":"Crafting","rank":755173,"level":76,"xp":1361818},{"id":14,"name":"Smithing","rank":1134401,"level":70,"xp":752866},{"id":15,"name":"Mining","rank":1219148,"level":70,"xp":780981},{"id":16,"name":"Herblore","rank":885348,"level":70,"xp":773142},{"id":17,"name":"Agility","rank":1335616,"level":67,"xp":573190},{"id":18,"name":"Thieving","rank":1169405,"level":61,"xp":322079},{"id":19,"name":"Slayer","rank":1312923,"level":66,"xp":513513},{"id":20,"name":"Farming","rank":323538,"level":96,"xp":10401993},{"id":21,"name":"Runecraft","rank":914316,"level":60,"xp":278786},{"id":22,"name":"Hunter","rank":686004,"level":74,"xp":1113181},{"id":23,"name":"Construction","rank":353201,"level":84,"xp":2993270}]