[{"id":0,"name":"Overall","rank":767600,"level":1800,"xp":56183690},{"id":1,"name":"Attack","rank":1200169,"level":80,"xp":2012326},{"id":2,"name":"Defence","rank":1230000,"level":76,"xp":1466715},{"id":3,"name":"Strength","rank":1178226,"level":88,"xp":4547379},{"id":4,"name":"Hitpoints","rank":1201843,"level":87,"xp":4345959},{"id":5,"name":"Ranged","rank":1087136,"level":88,"xp":4389730},{"id":6,"name":"Prayer","rank":552864,"level":80,"xp":2041104},{"id":7,"name":"Magic","rank":1307288,"level":83,"xp":2743228},{"id":8,"name":"Cooking","rank":1127817,"level":75,"xp":1221347},{"id":9,"name":"Woodcutting","rank":720152,"level":80,"xp":2088391},{"id":10,"name":"Fletching","rank":798017,"level":80,"xp":1989091},{"id":11,"name":"Fishing","rank":1265164,"level":70,"xp":756463},{"id":12,"name":"Firemaking","rank":1217563,"level":75,"xp":1244603},{"id":13,"name":"Crafting","rank":768260,"level":76,"xp":1446809},{"id":14,"name":"Smithing","rank":1049897,"level":71,"xp":826119},{"id":15,"name":"Mining","rank":955662,"level":74,"xp":1151957},{"id":16,"name":"Herblore","rank":783063,"level":72,"xp":917620},{"id":17,"name":"Agility","rank":1026029,"level":72,"xp":901644},{"id":18,"name":"Thieving","rank":685627,"level":75,"xp":1294167},{"id":19,"name":"Slayer","rank":1111322,"level":72,"xp":929844},{"id":20,"name":"Farming","rank":142149,"level":99,"xp":14792531},{"id":21,"name":"Runecraft","rank":696715,"level":67,"xp":552611},{"id":22,"name":"Hunter","rank":618090,"level":76,"xp":1455999},{"id":23,"name":"Construction","rank":342120,"level":84,"xp":3068053}]