[{"id":0,"name":"Overall","rank":972149,"level":1672,"xp":32845901},{"id":1,"name":"Attack","rank":1617719,"level":71,"xp":893414},{"id":2,"name":"Defence","rank":1441421,"level":71,"xp":896628},{"id":3,"name":"Strength","rank":1819606,"level":74,"xp":1160552},{"id":4,"name":"Hitpoints","rank":1745394,"level":76,"xp":1433382},{"id":5,"name":"Ranged","rank":1748891,"level":75,"xp":1231552},{"id":6,"name":"Prayer","rank":1109098,"level":70,"xp":770796},{"id":7,"name":"Magic","rank":1814786,"level":73,"xp":1028480},{"id":8,"name":"Cooking","rank":1120226,"level":74,"xp":1117367},{"id":9,"name":"Woodcutting","rank":820749,"level":77,"xp":1595601},{"id":10,"name":"Fletching","rank":804945,"level":78,"xp":1741065},{"id":11,"name":"Fishing","rank":1331386,"level":68,"xp":654170},{"id":12,"name":"Firemaking","rank":1346518,"level":71,"xp":855554},{"id":13,"name":"Crafting","rank":755178,"level":76,"xp":1361218},{"id":14,"name":"Smithing","rank":1133963,"level":70,"xp":752866},{"id":15,"name":"Mining","rank":1218674,"level":70,"xp":780981},{"id":16,"name":"Herblore","rank":884960,"level":70,"xp":773142},{"id":17,"name":"Agility","rank":1335100,"level":67,"xp":573190},{"id":18,"name":"Thieving","rank":1168906,"level":61,"xp":322079},{"id":19,"name":"Slayer","rank":1312588,"level":66,"xp":513513},{"id":20,"name":"Farming","rank":329116,"level":96,"xp":10018794},{"id":21,"name":"Runecraft","rank":913932,"level":60,"xp":278786},{"id":22,"name":"Hunter","rank":691935,"level":74,"xp":1099501},{"id":23,"name":"Construction","rank":353058,"level":84,"xp":2993270}]