[{"id":0,"name":"Overall","rank":523422,"level":1951,"xp":83034957},{"id":1,"name":"Attack","rank":1243356,"level":80,"xp":2073943},{"id":2,"name":"Defence","rank":988811,"level":82,"xp":2460471},{"id":3,"name":"Strength","rank":1065995,"level":91,"xp":6111973},{"id":4,"name":"Hitpoints","rank":899407,"level":94,"xp":8655592},{"id":5,"name":"Ranged","rank":462535,"level":99,"xp":14898256},{"id":6,"name":"Prayer","rank":550285,"level":80,"xp":2147097},{"id":7,"name":"Magic","rank":1189917,"level":86,"xp":3678670},{"id":8,"name":"Cooking","rank":1130424,"level":76,"xp":1339845},{"id":9,"name":"Woodcutting","rank":645925,"level":83,"xp":2741905},{"id":10,"name":"Fletching","rank":794051,"level":80,"xp":2074594},{"id":11,"name":"Fishing","rank":1013457,"level":75,"xp":1229529},{"id":12,"name":"Firemaking","rank":1240021,"level":75,"xp":1280629},{"id":13,"name":"Crafting","rank":789715,"level":77,"xp":1531105},{"id":14,"name":"Smithing","rank":456143,"level":84,"xp":2973943},{"id":15,"name":"Mining","rank":963812,"level":75,"xp":1245211},{"id":16,"name":"Herblore","rank":830495,"level":72,"xp":918112},{"id":17,"name":"Agility","rank":936226,"level":73,"xp":1045900},{"id":18,"name":"Thieving","rank":659061,"level":77,"xp":1492352},{"id":19,"name":"Slayer","rank":953510,"level":77,"xp":1515507},{"id":20,"name":"Farming","rank":130497,"level":99,"xp":15505333},{"id":21,"name":"Runecraft","rank":548428,"level":73,"xp":997699},{"id":22,"name":"Hunter","rank":577984,"level":79,"xp":1827265},{"id":23,"name":"Construction","rank":354585,"level":84,"xp":3163427},{"id":24,"name":"Sailing","rank":69908,"level":80,"xp":2126599}]