[{"id":0,"name":"Overall","rank":970072,"level":1674,"xp":35676526},{"id":1,"name":"Attack","rank":1619702,"level":71,"xp":894324},{"id":2,"name":"Defence","rank":1443206,"level":71,"xp":897702},{"id":3,"name":"Strength","rank":1821555,"level":74,"xp":1162686},{"id":4,"name":"Hitpoints","rank":1746079,"level":76,"xp":1438171},{"id":5,"name":"Ranged","rank":1747361,"level":75,"xp":1236022},{"id":6,"name":"Prayer","rank":1110919,"level":70,"xp":770796},{"id":7,"name":"Magic","rank":1812618,"level":73,"xp":1039536},{"id":8,"name":"Cooking","rank":1121818,"level":74,"xp":1117367},{"id":9,"name":"Woodcutting","rank":822143,"level":77,"xp":1595601},{"id":10,"name":"Fletching","rank":805985,"level":78,"xp":1741065},{"id":11,"name":"Fishing","rank":1333099,"level":68,"xp":654170},{"id":12,"name":"Firemaking","rank":1348838,"level":71,"xp":855554},{"id":13,"name":"Crafting","rank":755927,"level":76,"xp":1362618},{"id":14,"name":"Smithing","rank":1135923,"level":70,"xp":752866},{"id":15,"name":"Mining","rank":1220790,"level":70,"xp":780981},{"id":16,"name":"Herblore","rank":886153,"level":70,"xp":773412},{"id":17,"name":"Agility","rank":1337591,"level":67,"xp":573190},{"id":18,"name":"Thieving","rank":1171234,"level":61,"xp":322079},{"id":19,"name":"Slayer","rank":1311649,"level":66,"xp":517620},{"id":20,"name":"Farming","rank":301712,"level":98,"xp":12787152},{"id":21,"name":"Runecraft","rank":915850,"level":60,"xp":278786},{"id":22,"name":"Hunter","rank":680089,"level":74,"xp":1131558},{"id":23,"name":"Construction","rank":353929,"level":84,"xp":2993270}]