[{"id":0,"name":"Overall","rank":972294,"level":1672,"xp":32999538},{"id":1,"name":"Attack","rank":1618034,"level":71,"xp":893414},{"id":2,"name":"Defence","rank":1441691,"level":71,"xp":896628},{"id":3,"name":"Strength","rank":1819969,"level":74,"xp":1160552},{"id":4,"name":"Hitpoints","rank":1745867,"level":76,"xp":1433382},{"id":5,"name":"Ranged","rank":1749194,"level":75,"xp":1231552},{"id":6,"name":"Prayer","rank":1109290,"level":70,"xp":770796},{"id":7,"name":"Magic","rank":1815075,"level":73,"xp":1028480},{"id":8,"name":"Cooking","rank":1120409,"level":74,"xp":1117367},{"id":9,"name":"Woodcutting","rank":820901,"level":77,"xp":1595601},{"id":10,"name":"Fletching","rank":805095,"level":78,"xp":1741065},{"id":11,"name":"Fishing","rank":1331564,"level":68,"xp":654170},{"id":12,"name":"Firemaking","rank":1346777,"level":71,"xp":855554},{"id":13,"name":"Crafting","rank":755215,"level":76,"xp":1361418},{"id":14,"name":"Smithing","rank":1134168,"level":70,"xp":752866},{"id":15,"name":"Mining","rank":1218923,"level":70,"xp":780981},{"id":16,"name":"Herblore","rank":885141,"level":70,"xp":773142},{"id":17,"name":"Agility","rank":1335391,"level":67,"xp":573190},{"id":18,"name":"Thieving","rank":1169155,"level":61,"xp":322079},{"id":19,"name":"Slayer","rank":1312753,"level":66,"xp":513513},{"id":20,"name":"Farming","rank":326809,"level":96,"xp":10167671},{"id":21,"name":"Runecraft","rank":914123,"level":60,"xp":278786},{"id":22,"name":"Hunter","rank":689830,"level":74,"xp":1104061},{"id":23,"name":"Construction","rank":353130,"level":84,"xp":2993270}]